xvideos_api/__init__.py
xvideos_api/xvideos_api.py
xvideos_api/modules/__init__.py
xvideos_api/modules/consts.py
xvideos_api/modules/exceptions.py
xvideos_api/modules/sorting.py
xvideos_api/tests/__init__.py
xvideos_api/tests/conftest.py
xvideos_api/tests/test_download.py
xvideos_api/tests/test_pornstar.py
xvideos_api/tests/test_search.py
xvideos_api/tests/test_video.py
xvideos_api_async-1.5.3.1.dist-info/LICENSE
xvideos_api_async-1.5.3.1.dist-info/METADATA
xvideos_api_async-1.5.3.1.dist-info/WHEEL
xvideos_api_async-1.5.3.1.dist-info/entry_points.txt
xvideos_api_async-1.5.3.1.dist-info/top_level.txt
xvideos_api_async-1.5.3.1.dist-info/RECORD
